trendify/CLI.py
trendify/__init__.py
trendify/examples.py
trendify/gallery.py
trendify/local_server.py
trendify/plotly_dashboard.py
trendify/production_server.py
trendify/server.py
trendify/streamlit.py
trendify/api/__init__.py
trendify/api/api.py
trendify/api/base/__init__.py
trendify/api/base/data_product.py
trendify/api/base/helpers.py
trendify/api/base/pen.py
trendify/api/formats/__init__.py
trendify/api/formats/format2d.py
trendify/api/formats/table.py
trendify/api/generator/__init__.py
trendify/api/generator/data_product_collection.py
trendify/api/generator/data_product_generator.py
trendify/api/generator/histogrammer.py
trendify/api/generator/table_builder.py
trendify/api/generator/xy_data_plotter.py
trendify/api/plotting/__init__.py
trendify/api/plotting/axline.py
trendify/api/plotting/histogram.py
trendify/api/plotting/plotting.py
trendify/api/plotting/point.py
trendify/api/plotting/trace.py
trendify/api/styling/__init__.py
trendify/api/styling/grid.py
trendify/api/styling/legend.py
trendify/api/styling/marker.py
trendify/assets/logo.svg
trendify/assets/logo_white_bg.svg
trendify-1.2.11.dist-info/METADATA
trendify-1.2.11.dist-info/WHEEL
trendify-1.2.11.dist-info/entry_points.txt
trendify-1.2.11.dist-info/RECORD
